{"visible": {"type": 0, "list_id": 0}, "created_at": "Sat Oct 07 00:01:00 +0800 2023", "id": 4953995624056320, "idstr": "4953995624056320", "mid": "4953995624056320", "mblogid": "NmEFIh1ew", "user": {"id": 5679399630, "idstr": "5679399630", "pc_new": 7, "screen_name": "英雄联盟神吐槽", "profile_image_url": "https://tvax2.sinaimg.cn/crop.0.0.439.439.50/006cmbhQly8h8uglinec1j30c70c73yz.jpg?KID=imgbed,tva&amp;Expires=1704593941&amp;ssig=KKsz8aAxXl", "profile_url": "/u/5679399630", "verified": true, "verified_type": 0, "domain": "", "weihao": "", "verified_type_ext": 1, "avatar_large": "https://tvax2.sinaimg.cn/crop.0.0.439.439.180/006cmbhQly8h8uglinec1j30c70c73yz.jpg?KID=imgbed,tva&amp;Expires=1704593941&amp;ssig=t1JKFtdLYv", "avatar_hd": "https://tvax2.sinaimg.cn/crop.0.0.439.439.1024/006cmbhQly8h8uglinec1j30c70c73yz.jpg?KID=imgbed,tva&amp;Expires=1704593941&amp;ssig=U3FIOtJF00", "follow_me": false, "following": false, "mbrank": 2, "mbtype": 12, "v_plus": 1, "planet_video": false, "icon_list": [{"type": "vip", "data": {"mbrank": 2, "mbtype": 12, "svip": 1, "vvip": 1}}]}, "can_edit": false, "text_raw": "国庆假期结束，盘点一下电竞圈的选手、解说女友们都去了哪些地方[吃瓜]\n\nGALA女友 尤里绘 在悉尼读书 未出去旅游；\n\nMing绯闻女友 1saye 法国；\n\nRookie女友小钰 很少出门，昨天KTV团建；\n\n#rookie##ming##超话创作官# ​​​", "textLength": 202, "annotations": [{"photo_sub_type": "0,0,0,0,0,0,0,0,0"}, [], {"super_exparams": "{\"system_pic_only\":0}"}, {"client_mblogid": "9320ff8b-a7ef-437d-bff1-eab97f901367"}, {"source_text": "", "phone_id": "-1"}, {"mapi_request": true}], "source": "", "favorited": false, "rid": "16_0_50_5136056410942293653_0_0_0", "pic_ids": ["006cmbhQgy1hilvj1qzutj30lw0gqdj5", "006cmbhQgy1hilvj31pnfj32c03404qs", "006cmbhQgy1hilvj4toejj32c0340b2b", "006cmbhQgy1hilvj61mecj30sz0mcdlq", "006cmbhQgy1hilvj6fmsej30h70etwhi", "006cmbhQgy1hilvj6u7b0j30h00flgof", "006cmbhQgy1hilvj75csnj30ni0ryjug", "006cmbhQgy1hilvj7h9p2j30u0140agj", "006cmbhQgy1hilvj7sw80j30u0140wlo"], "pic_focus_point": [{"focus_point": {"left": 0.38405797, "top": 0.06630435, "width": 0.5797101, "height": 0.57608694}, "pic_id": "006cmbhQgy1hilvj7sw80j30u0140wlo"}, {"focus_point": {"left": 0.39710146, "top": 0.24021739, "width": 0.41449276, "height": 0.375}, "pic_id": "006cmbhQgy1hilvj7h9p2j30u0140agj"}, {"focus_point": {"left": 0.0768116, "top": 0.2914634, "width": 0.42028984, "height": 0.597561}, "pic_id": "006cmbhQgy1hilvj75csnj30ni0ryjug"}, {"focus_point": {"left": 0.5866013, "top": 0.20677362, "width": 0.22875817, "height": 0.20677362}, "pic_id": "006cmbhQgy1hilvj6u7b0j30h00flgof"}, {"focus_point": {"left": 0.3441034, "top": 0.15947467, "width": 0.14378029, "height": 0.18949343}, "pic_id": "006cmbhQgy1hilvj6fmsej30h70etwhi"}, {"focus_point": {"left": 0.2884058, "top": 0.43609023, "width": 0.12463768, "height": 0.16729324}, "pic_id": "006cmbhQgy1hilvj61mecj30sz0mcdlq"}, {"focus_point": {"left": 0.47826087, "top": 0.3478261, "width": 0.14637682, "height": 0.12934783}, "pic_id": "006cmbhQgy1hilvj4toejj32c0340b2b"}, {"focus_point": {"left": 0.020786805, "top": 0.2655901, "width": 0.9792131, "height": 0.7344098}, "pic_id": "006cmbhQgy1hilvj31pnfj32c03404qs"}, {"focus_point": {"left": 0.45072463, "top": 0.24478178, "width": 0.06811594, "height": 0.121442124}, "pic_id": "006cmbhQgy1hilvj1qzutj30lw0gqdj5"}], "pic_num": 9, "pic_infos": {"006cmbhQgy1hilvj1qzutj30lw0gqdj5": {"thumbnail": {"url": "https://wx3.sinaimg.cn/wap180/006cmbhQgy1hilvj1qzutj30lw0gqdj5.jpg", "width": 180, "height": 137, "cut_type": 1, "type": ""}, "bmiddle": {"url": "https://wx3.sinaimg.cn/wap360/006cmbhQgy1hilvj1qzutj30lw0gqdj5.jpg", "width": 360, "height": 274, "cut_type": 1, "type": ""}, "large": {"url": "https://wx3.sinaimg.cn/orj960/006cmbhQgy1hilvj1qzutj30lw0gqdj5.jpg", "width": 788, "height": 602, "cut_type": 1, "type": ""}, "original": {"url": "https://wx3.sinaimg.cn/orj1080/006cmbhQgy1hilvj1qzutj30lw0gqdj5.jpg", "width": 788, "height": 602, "cut_type": 1, "type": ""}, "largest": {"url": "https://wx3.sinaimg.cn/large/006cmbhQgy1hilvj1qzutj30lw0gqdj5.jpg", "width": 788, "height": 602, "cut_type": 1, "type": ""}, "mw2000": {"url": "https://wx3.sinaimg.cn/mw2000/006cmbhQgy1hilvj1qzutj30lw0gqdj5.jpg", "width": 788, "height": 602, "cut_type": 1, "type": ""}, "focus_point": {"left": 0.45072463, "top": 0.24478178, "width": 0.06811594, "height": 0.121442124}, "object_id": "1042018:b55b6a897bf1a93df91aad83a340a71a", "pic_id": "006cmbhQgy1hilvj1qzutj30lw0gqdj5", "photo_tag": 0, "type": "pic", "pic_status": 1}, "006cmbhQgy1hilvj31pnfj32c03404qs": {"thumbnail": {"url": "https://wx3.sinaimg.cn/wap180/006cmbhQgy1hilvj31pnfj32c03404qs.jpg", "width": 135, "height": 180, "cut_type": 1, "type": ""}, "bmiddle": {"url": "https://wx3.sinaimg.cn/wap360/006cmbhQgy1hilvj31pnfj32c03404qs.jpg", "width": 270, "height": 360, "cut_type": 1, "type": ""}, "large": {"url": "https://wx3.sinaimg.cn/orj960/006cmbhQgy1hilvj31pnfj32c03404qs.jpg", "width": 960, "height": 1279, "cut_type": 1, "type": ""}, "original": {"url": "https://wx3.sinaimg.cn/orj1080/006cmbhQgy1hilvj31pnfj32c03404qs.jpg", "width": 1080, "height": 1439, "cut_type": 1, "type": ""}, "largest": {"url": "https://wx3.sinaimg.cn/large/006cmbhQgy1hilvj31pnfj32c03404qs.jpg", "width": 2048, "height": 2730, "cut_type": 1, "type": ""}, "mw2000": {"url": "https://wx3.sinaimg.cn/mw2000/006cmbhQgy1hilvj31pnfj32c03404qs.jpg", "width": 2000, "height": 2666, "cut_type": 1, "type": ""}, "focus_point": {"left": 0.020786805, "top": 0.2655901, "width": 0.9792131, "height": 0.7344098}, "object_id": "1042018:69af4c4bd08d994478216203295da50f", "pic_id": "006cmbhQgy1hilvj31pnfj32c03404qs", "photo_tag": 0, "type": "pic", "pic_status": 1}, "006cmbhQgy1hilvj4toejj32c0340b2b": {"thumbnail": {"url": "https://wx4.sinaimg.cn/wap180/006cmbhQgy1hilvj4toejj32c0340b2b.jpg", "width": 135, "height": 180, "cut_type": 1, "type": ""}, "bmiddle": {"url": "https://wx4.sinaimg.cn/wap360/006cmbhQgy1hilvj4toejj32c0340b2b.jpg", "width": 270, "height": 360, "cut_type": 1, "type": ""}, "large": {"url": "https://wx4.sinaimg.cn/orj960/006cmbhQgy1hilvj4toejj32c0340b2b.jpg", "width": 960, "height": 1279, "cut_type": 1, "type": ""}, "original": {"url": "https://wx4.sinaimg.cn/orj1080/006cmbhQgy1hilvj4toejj32c0340b2b.jpg", "width": 1080, "height": 1439, "cut_type": 1, "type": ""}, "largest": {"url": "https://wx4.sinaimg.cn/large/006cmbhQgy1hilvj4toejj32c0340b2b.jpg", "width": 2048, "height": 2730, "cut_type": 1, "type": ""}, "mw2000": {"url": "https://wx4.sinaimg.cn/mw2000/006cmbhQgy1hilvj4toejj32c0340b2b.jpg", "width": 2000, "height": 2666, "cut_type": 1, "type": ""}, "focus_point": {"left": 0.47826087, "top": 0.3478261, "width": 0.14637682, "height": 0.12934783}, "object_id": "1042018:5d387446493e6693e705e5cb5b0341f9", "pic_id": "006cmbhQgy1hilvj4toejj32c0340b2b", "photo_tag": 0, "type": "pic", "pic_status": 1}, "006cmbhQgy1hilvj61mecj30sz0mcdlq": {"thumbnail": {"url": "https://wx3.sinaimg.cn/wap180/006cmbhQgy1hilvj61mecj30sz0mcdlq.jpg", "width": 180, "height": 138, "cut_type": 1, "type": ""}, "bmiddle": {"url": "https://wx3.sinaimg.cn/wap360/006cmbhQgy1hilvj61mecj30sz0mcdlq.jpg", "width": 360, "height": 277, "cut_type": 1, "type": ""}, "large": {"url": "https://wx3.sinaimg.cn/orj960/006cmbhQgy1hilvj61mecj30sz0mcdlq.jpg", "width": 1043, "height": 804, "cut_type": 1, "type": ""}, "original": {"url": "https://wx3.sinaimg.cn/orj1080/006cmbhQgy1hilvj61mecj30sz0mcdlq.jpg", "width": 1043, "height": 804, "cut_type": 1, "type": ""}, "largest": {"url": "https://wx3.sinaimg.cn/large/006cmbhQgy1hilvj61mecj30sz0mcdlq.jpg", "width": 1043, "height": 804, "cut_type": 1, "type": ""}, "mw2000": {"url": "https://wx3.sinaimg.cn/mw2000/006cmbhQgy1hilvj61mecj30sz0mcdlq.jpg", "width": 1043, "height": 804, "cut_type": 1, "type": ""}, "focus_point": {"left": 0.2884058, "top": 0.43609023, "width": 0.12463768, "height": 0.16729324}, "object_id": "1042018:b25487505f9e8b7fbab489c09ebf3758", "pic_id": "006cmbhQgy1hilvj61mecj30sz0mcdlq", "photo_tag": 0, "type": "pic", "pic_status": 1}, "006cmbhQgy1hilvj6fmsej30h70etwhi": {"thumbnail": {"url": "https://wx2.sinaimg.cn/wap180/006cmbhQgy1hilvj6fmsej30h70etwhi.jpg", "width": 180, "height": 154, "cut_type": 1, "type": ""}, "bmiddle": {"url": "https://wx2.sinaimg.cn/wap360/006cmbhQgy1hilvj6fmsej30h70etwhi.jpg", "width": 360, "height": 309, "cut_type": 1, "type": ""}, "large": {"url": "https://wx2.sinaimg.cn/orj960/006cmbhQgy1hilvj6fmsej30h70etwhi.jpg", "width": 619, "height": 533, "cut_type": 1, "type": ""}, "original": {"url": "https://wx2.sinaimg.cn/orj1080/006cmbhQgy1hilvj6fmsej30h70etwhi.jpg", "width": 619, "height": 533, "cut_type": 1, "type": ""}, "largest": {"url": "https://wx2.sinaimg.cn/large/006cmbhQgy1hilvj6fmsej30h70etwhi.jpg", "width": 619, "height": 533, "cut_type": 1, "type": ""}, "mw2000": {"url": "https://wx2.sinaimg.cn/mw2000/006cmbhQgy1hilvj6fmsej30h70etwhi.jpg", "width": 619, "height": 533, "cut_type": 1, "type": ""}, "focus_point": {"left": 0.3441034, "top": 0.15947467, "width": 0.14378029, "height": 0.18949343}, "object_id": "1042018:fb6430eef7a7c2bf79f7aecaffaa8756", "pic_id": "006cmbhQgy1hilvj6fmsej30h70etwhi", "photo_tag": 0, "type": "pic", "pic_status": 1}, "006cmbhQgy1hilvj6u7b0j30h00flgof": {"thumbnail": {"url": "https://wx3.sinaimg.cn/wap180/006cmbhQgy1hilvj6u7b0j30h00flgof.jpg", "width": 180, "height": 165, "cut_type": 1, "type": ""}, "bmiddle": {"url": "https://wx3.sinaimg.cn/wap360/006cmbhQgy1hilvj6u7b0j30h00flgof.jpg", "width": 360, "height": 330, "cut_type": 1, "type": ""}, "large": {"url": "https://wx3.sinaimg.cn/orj960/006cmbhQgy1hilvj6u7b0j30h00flgof.jpg", "width": 612, "height": 561, "cut_type": 1, "type": ""}, "original": {"url": "https://wx3.sinaimg.cn/orj1080/006cmbhQgy1hilvj6u7b0j30h00flgof.jpg", "width": 612, "height": 561, "cut_type": 1, "type": ""}, "largest": {"url": "https://wx3.sinaimg.cn/large/006cmbhQgy1hilvj6u7b0j30h00flgof.jpg", "width": 612, "height": 561, "cut_type": 1, "type": ""}, "mw2000": {"url": "https://wx3.sinaimg.cn/mw2000/006cmbhQgy1hilvj6u7b0j30h00flgof.jpg", "width": 612, "height": 561, "cut_type": 1, "type": ""}, "focus_point": {"left": 0.5866013, "top": 0.20677362, "width": 0.22875817, "height": 0.20677362}, "object_id": "1042018:210ccb392776be76409033fe9fecabb3", "pic_id": "006cmbhQgy1hilvj6u7b0j30h00flgof", "photo_tag": 0, "type": "pic", "pic_status": 1}, "006cmbhQgy1hilvj75csnj30ni0ryjug": {"thumbnail": {"url": "https://wx4.sinaimg.cn/wap180/006cmbhQgy1hilvj75csnj30ni0ryjug.jpg", "width": 151, "height": 180, "cut_type": 1, "type": ""}, "bmiddle": {"url": "https://wx4.sinaimg.cn/wap360/006cmbhQgy1hilvj75csnj30ni0ryjug.jpg", "width": 302, "height": 360, "cut_type": 1, "type": ""}, "large": {"url": "https://wx4.sinaimg.cn/orj960/006cmbhQgy1hilvj75csnj30ni0ryjug.jpg", "width": 846, "height": 1006, "cut_type": 1, "type": ""}, "original": {"url": "https://wx4.sinaimg.cn/orj1080/006cmbhQgy1hilvj75csnj30ni0ryjug.jpg", "width": 846, "height": 1006, "cut_type": 1, "type": ""}, "largest": {"url": "https://wx4.sinaimg.cn/large/006cmbhQgy1hilvj75csnj30ni0ryjug.jpg", "width": 846, "height": 1006, "cut_type": 1, "type": ""}, "mw2000": {"url": "https://wx4.sinaimg.cn/mw2000/006cmbhQgy1hilvj75csnj30ni0ryjug.jpg", "width": 846, "height": 1006, "cut_type": 1, "type": ""}, "focus_point": {"left": 0.0768116, "top": 0.2914634, "width": 0.42028984, "height": 0.597561}, "object_id": "1042018:f93401c56757bb2b90c0e6747429f7e4", "pic_id": "006cmbhQgy1hilvj75csnj30ni0ryjug", "photo_tag": 0, "type": "pic", "pic_status": 1}, "006cmbhQgy1hilvj7h9p2j30u0140agj": {"thumbnail": {"url": "https://wx2.sinaimg.cn/wap180/006cmbhQgy1hilvj7h9p2j30u0140agj.jpg", "width": 135, "height": 180, "cut_type": 1, "type": ""}, "bmiddle": {"url": "https://wx2.sinaimg.cn/wap360/006cmbhQgy1hilvj7h9p2j30u0140agj.jpg", "width": 270, "height": 360, "cut_type": 1, "type": ""}, "large": {"url": "https://wx2.sinaimg.cn/orj960/006cmbhQgy1hilvj7h9p2j30u0140agj.jpg", "width": 960, "height": 1280, "cut_type": 1, "type": ""}, "original": {"url": "https://wx2.sinaimg.cn/orj1080/006cmbhQgy1hilvj7h9p2j30u0140agj.jpg", "width": 1080, "height": 1440, "cut_type": 1, "type": ""}, "largest": {"url": "https://wx2.sinaimg.cn/large/006cmbhQgy1hilvj7h9p2j30u0140agj.jpg", "width": 1080, "height": 1440, "cut_type": 1, "type": ""}, "mw2000": {"url": "https://wx2.sinaimg.cn/mw2000/006cmbhQgy1hilvj7h9p2j30u0140agj.jpg", "width": 1080, "height": 1440, "cut_type": 1, "type": ""}, "focus_point": {"left": 0.39710146, "top": 0.24021739, "width": 0.41449276, "height": 0.375}, "object_id": "1042018:d5d3f59558d245fc1cb4c1e5060d9522", "pic_id": "006cmbhQgy1hilvj7h9p2j30u0140agj", "photo_tag": 0, "type": "pic", "pic_status": 1}, "006cmbhQgy1hilvj7sw80j30u0140wlo": {"thumbnail": {"url": "https://wx3.sinaimg.cn/wap180/006cmbhQgy1hilvj7sw80j30u0140wlo.jpg", "width": 135, "height": 180, "cut_type": 1, "type": ""}, "bmiddle": {"url": "https://wx3.sinaimg.cn/wap360/006cmbhQgy1hilvj7sw80j30u0140wlo.jpg", "width": 270, "height": 360, "cut_type": 1, "type": ""}, "large": {"url": "https://wx3.sinaimg.cn/orj960/006cmbhQgy1hilvj7sw80j30u0140wlo.jpg", "width": 960, "height": 1280, "cut_type": 1, "type": ""}, "original": {"url": "https://wx3.sinaimg.cn/orj1080/006cmbhQgy1hilvj7sw80j30u0140wlo.jpg", "width": 1080, "height": 1440, "cut_type": 1, "type": ""}, "largest": {"url": "https://wx3.sinaimg.cn/large/006cmbhQgy1hilvj7sw80j30u0140wlo.jpg", "width": 1080, "height": 1440, "cut_type": 1, "type": ""}, "mw2000": {"url": "https://wx3.sinaimg.cn/mw2000/006cmbhQgy1hilvj7sw80j30u0140wlo.jpg", "width": 1080, "height": 1440, "cut_type": 1, "type": ""}, "focus_point": {"left": 0.38405797, "top": 0.06630435, "width": 0.5797101, "height": 0.57608694}, "object_id": "1042018:44e339414c737757504adf0209fafc2b", "pic_id": "006cmbhQgy1hilvj7sw80j30u0140wlo", "photo_tag": 0, "type": "pic", "pic_status": 1}}, "is_paid": false, "pic_bg_new": "https://n.sinaimg.cn/default/944aebbe/20231129/pic_hypertalk_diamond.png", "mblog_vip_type": 0, "number_display_strategy": {"apply_scenario_flag": 3, "display_text_min_number": 1000000, "display_text": "100万+"}, "title_source": {"name": "英雄联盟超话", "url": "sinaweibo://pageinfo?pageid=10080854838a6bbae2a14b0fb0c7905f6a070a&amp;extparam=英雄联盟", "image": "http://wx4.sinaimg.cn/thumbnail/e5cc3119ly8hkl88udf9kj20rs0rs76q.jpg"}, "reposts_count": 21, "comments_count": 170, "attitudes_count": 1005, "attitudes_status": 0, "isLongText": false, "mlevel": 0, "content_auth": 0, "is_show_bulletin": 3, "comment_manage_info": {"comment_permission_type": -1, "approval_comment_type": 0, "comment_sort_type": 0}, "screen_name_suffix_new": [{"content": "英雄联盟神吐槽", "remark": "", "color": "FF333333", "dark_color": "FFD3D3D3", "type": 1, "truncation": {"mode": 1}}, {"content": "英雄联盟超话", "color": "FF507DAF", "dark_color": "FF7691b9", "type": 2, "scheme": "sinaweibo://pageinfo?pageid=10080854838a6bbae2a14b0fb0c7905f6a070a&amp;extparam=英雄联盟&amp;extension=%7B%22mblog_object_ref%22%3A%22topic%22%7D", "icons": [{"url": "https://h5.sinaimg.cn/upload/1000/808/2020/02/17/andriod_chaohua_header.png", "scheme": "sinaweibo://pageinfo?pageid=10080854838a6bbae2a14b0fb0c7905f6a070a&amp;extparam=英雄联盟", "cleaned": true}], "icons_location": 0, "truncation": {"mode": 1, "keep_end_size": 2}, "actionlog": {"act_code": 1404, "oid": "1022:10080854838a6bbae2a14b0fb0c7905f6a070a", "uicode": "", "luicode": "", "fid": "1076035679399630_-_WEIBO_SECOND_PROFILE_WEIBO", "ext": "mid:4953995624056320|source_type:3|uid:6839654475|analysis_extra:follow:0|new_style:1"}, "cleaned": true}], "share_repost_type": 0, "topic_struct": [{"title": "", "topic_url": "sinaweibo://searchall?containerid=231522&amp;q=%23rookie%23&amp;isnewpage=1", "topic_title": "rookie", "actionlog": {"act_type": 1, "act_code": 300, "oid": "1022:231522891fbc7a93834f52f62785c3dddcda05", "uuid": 4213161182926014, "cardid": "", "lcardid": "", "uicode": "", "luicode": "", "fid": "1076035679399630_-_WEIBO_SECOND_PROFILE_WEIBO", "lfid": "", "ext": "mid:4953995624056320|rid:16_0_50_5136056410942293653_0_0_0|short_url:|long_url:|comment_id:|miduid:5679399630|rootmid:4953995624056320|rootuid:5679399630|authorid:|uuid:4213161182926014|is_ad_weibo:0"}}, {"title": "", "topic_url": "sinaweibo://searchall?containerid=231522&amp;q=%23ming%23&amp;isnewpage=1", "topic_title": "ming", "actionlog": {"act_type": 1, "act_code": 300, "oid": "1022:23152295c90aa47733b9023c318d9914606339", "uuid": 4213206472987151, "cardid": "", "lcardid": "", "uicode": "", "luicode": "", "fid": "1076035679399630_-_WEIBO_SECOND_PROFILE_WEIBO", "lfid": "", "ext": "mid:4953995624056320|rid:16_0_50_5136056410942293653_0_0_0|short_url:|long_url:|comment_id:|miduid:5679399630|rootmid:4953995624056320|rootuid:5679399630|authorid:|uuid:4213206472987151|is_ad_weibo:0"}}, {"title": "", "topic_url": "sinaweibo://searchall?containerid=231522&amp;q=%23%E8%B6%85%E8%AF%9D%E5%88%9B%E4%BD%9C%E5%AE%98%23&amp;extparam=%23%E8%B6%85%E8%AF%9D%E5%88%9B%E4%BD%9C%E5%AE%98%23", "topic_title": "超话创作官", "actionlog": {"act_type": 1, "act_code": 300, "oid": "1022:23152200ce39d9a162d3e7507a7f0ef43cfc63", "uuid": 4757757248143546, "cardid": "", "lcardid": "", "uicode": "", "luicode": "", "fid": "1076035679399630_-_WEIBO_SECOND_PROFILE_WEIBO", "lfid": "", "ext": "mid:4953995624056320|rid:16_0_50_5136056410942293653_0_0_0|short_url:|long_url:|comment_id:|miduid:5679399630|rootmid:4953995624056320|rootuid:5679399630|authorid:|uuid:4757757248143546|is_ad_weibo:0"}}], "url_struct": [{"url_title": "英雄联盟超话", "url_type_pic": "https://h5.sinaimg.cn/upload/100/959/2020/05/09/timeline_card_small_super.png", "ori_url": "sinaweibo://pageinfo?containerid=10080854838a6bbae2a14b0fb0c7905f6a070a&amp;extparam=英雄联盟&amp;extension=%7B%22mblog_object_ref%22%3A%22content%22%7D", "page_id": "10080854838a6bbae2a14b0fb0c7905f6a070a", "short_url": "#英雄联盟[超话]#", "long_url": "", "url_type": "", "result": false, "actionlog": {"act_type": 1, "act_code": 300, "oid": "1022:10080854838a6bbae2a14b0fb0c7905f6a070a", "uuid": 3542518124787965, "cardid": "", "lcardid": "", "uicode": "", "luicode": "", "fid": "1076035679399630_-_WEIBO_SECOND_PROFILE_WEIBO", "lfid": "", "ext": "mid:4953995624056320|rid:16_0_50_5136056410942293653_0_0_0|short_url:|long_url:|comment_id:|miduid:5679399630|rootmid:4953995624056320|rootuid:5679399630|authorid:|uuid:3542518124787965|is_ad_weibo:0|analysis_card:url_struct"}, "storage_type": "", "hide": 0, "object_type": "", "h5_target_url": "https://huati.weibo.com/k/英雄联盟?from=1FFFF96039&amp;weiboauthoruid=5679399630", "need_save_obj": 0}], "mblogtype": 0, "showFeedRepost": false, "showFeedComment": false, "pictureViewerSign": false, "showPictureViewer": false, "rcList": [], "text": "国庆假期结束，盘点一下电竞圈的选手、解说女友们都去了哪些地方&lt;img alt=\"[吃瓜]\" title=\"[吃瓜]\" src=\"https://face.t.sinajs.cn/t4/appstyle/expression/ext/normal/01/2018new_chigua_org.png\" /&gt;&lt;br /&gt;&lt;br /&gt;GALA女友 尤里绘 在悉尼读书 未出去旅游；&lt;br /&gt;&lt;br /&gt;Ming绯闻女友 1saye 法国；&lt;br /&gt;&lt;br /&gt;Rookie女友小钰 很少出门，昨天KTV团建；&lt;br /&gt;&lt;br /&gt;&lt;a href=\"//s.weibo.com/weibo?q=%23rookie%23\" target=\"_blank\"&gt;#rookie#&lt;/a&gt;&lt;a href=\"//s.weibo.com/weibo?q=%23ming%23\" target=\"_blank\"&gt;#ming#&lt;/a&gt;&lt;a href=\"//s.weibo.com/weibo?q=%23%E8%B6%85%E8%AF%9D%E5%88%9B%E4%BD%9C%E5%AE%98%23\" target=\"_blank\"&gt;#超话创作官#&lt;/a&gt; ​​​", "region_name": "发布于 江西", "customIcons": []}