{"visible": {"type": 0, "list_id": 0}, "created_at": "Thu Nov 16 19:34:27 +0800 2023", "id": 4968786448876113, "idstr": "4968786448876113", "mid": "4968786448876113", "mblogid": "NsRrSBf57", "user": {"id": 1103123315, "idstr": "1103123315", "pc_new": 0, "screen_name": "87树", "profile_image_url": "https://tvax2.sinaimg.cn/crop.0.0.1080.1080.50/41c05373ly8hlkxfljtnaj20u00u0778.jpg?KID=imgbed,tva&amp;Expires=1704655051&amp;ssig=mP%2FSc7p%2Bz1", "profile_url": "/u/1103123315", "verified": true, "verified_type": 0, "domain": "", "weihao": "", "verified_type_ext": 2, "avatar_large": "https://tvax2.sinaimg.cn/crop.0.0.1080.1080.180/41c05373ly8hlkxfljtnaj20u00u0778.jpg?KID=imgbed,tva&amp;Expires=1704655051&amp;ssig=5Vw411cK5N", "avatar_hd": "https://tvax2.sinaimg.cn/crop.0.0.1080.1080.1024/41c05373ly8hlkxfljtnaj20u00u0778.jpg?KID=imgbed,tva&amp;Expires=1704655051&amp;ssig=%2FjLfAbreZl", "follow_me": false, "following": false, "mbrank": 1, "mbtype": 12, "v_plus": 0, "planet_video": false, "icon_list": [{"type": "vip", "data": {"mbrank": 1, "mbtype": 12, "svip": 1, "vvip": 1}}]}, "can_edit": false, "text_raw": "九月已说过一念关山首播为网播。\n下周一起，蜀大侠×一念关山主题火锅店拉开宣传序幕。[小炭火][小炭火][小炭火]#刘诗诗一念关山# ​​​", "textLength": 120, "annotations": [{"photo_sub_type": "0,0"}, [], {"client_mblogid": "9ae57242-5736-4ac2-be3d-20c6bf326225"}, {"source_text": "", "phone_id": "-1"}, {"mapi_request": true}], "source": "", "favorited": false, "rid": "4_0_50_164789167795791383_0_0_0", "pic_ids": ["41c05373gy1hjx6cowbw3j20y40iu0uu", "41c05373gy1hjx6cq8vqej20u00qwq6m"], "pic_focus_point": [{"focus_point": {"left": 0.09918427, "top": 0.064358115, "width": 0.8380097, "height": 0.93564177}, "pic_id": "41c05373gy1hjx6cq8vqej20u00qwq6m"}, {"focus_point": {"left": 0.07101449, "top": 0.38582677, "width": 0.03188406, "height": 0.06824147}, "pic_id": "41c05373gy1hjx6cowbw3j20y40iu0uu"}], "pic_num": 2, "pic_infos": {"41c05373gy1hjx6cowbw3j20y40iu0uu": {"thumbnail": {"url": "https://wx2.sinaimg.cn/wap180/41c05373gy1hjx6cowbw3j20y40iu0uu.jpg", "width": 180, "height": 99, "cut_type": 1, "type": ""}, "bmiddle": {"url": "https://wx2.sinaimg.cn/wap360/41c05373gy1hjx6cowbw3j20y40iu0uu.jpg", "width": 360, "height": 198, "cut_type": 1, "type": ""}, "large": {"url": "https://wx2.sinaimg.cn/orj960/41c05373gy1hjx6cowbw3j20y40iu0uu.jpg", "width": 1228, "height": 678, "cut_type": 1, "type": ""}, "original": {"url": "https://wx2.sinaimg.cn/orj1080/41c05373gy1hjx6cowbw3j20y40iu0uu.jpg", "width": 1228, "height": 678, "cut_type": 1, "type": ""}, "largest": {"url": "https://wx2.sinaimg.cn/large/41c05373gy1hjx6cowbw3j20y40iu0uu.jpg", "width": 1228, "height": 678, "cut_type": 1, "type": ""}, "mw2000": {"url": "https://wx2.sinaimg.cn/mw2000/41c05373gy1hjx6cowbw3j20y40iu0uu.jpg", "width": 1228, "height": 678, "cut_type": 1, "type": ""}, "focus_point": {"left": 0.07101449, "top": 0.38582677, "width": 0.03188406, "height": 0.06824147}, "object_id": "1042018:f2843532ec446a638f97a26d0299ed57", "pic_id": "41c05373gy1hjx6cowbw3j20y40iu0uu", "photo_tag": 0, "type": "pic", "pic_status": 1}, "41c05373gy1hjx6cq8vqej20u00qwq6m": {"thumbnail": {"url": "https://wx2.sinaimg.cn/wap180/41c05373gy1hjx6cq8vqej20u00qwq6m.jpg", "width": 180, "height": 161, "cut_type": 1, "type": ""}, "bmiddle": {"url": "https://wx2.sinaimg.cn/wap360/41c05373gy1hjx6cq8vqej20u00qwq6m.jpg", "width": 360, "height": 322, "cut_type": 1, "type": ""}, "large": {"url": "https://wx2.sinaimg.cn/orj960/41c05373gy1hjx6cq8vqej20u00qwq6m.jpg", "width": 1071, "height": 960, "cut_type": 1, "type": ""}, "original": {"url": "https://wx2.sinaimg.cn/orj1080/41c05373gy1hjx6cq8vqej20u00qwq6m.jpg", "width": 1080, "height": 968, "cut_type": 1, "type": ""}, "largest": {"url": "https://wx2.sinaimg.cn/large/41c05373gy1hjx6cq8vqej20u00qwq6m.jpg", "width": 1080, "height": 968, "cut_type": 1, "type": ""}, "mw2000": {"url": "https://wx2.sinaimg.cn/mw2000/41c05373gy1hjx6cq8vqej20u00qwq6m.jpg", "width": 1080, "height": 968, "cut_type": 1, "type": ""}, "focus_point": {"left": 0.09918427, "top": 0.064358115, "width": 0.8380097, "height": 0.93564177}, "object_id": "1042018:2ab76f4af590e7b808eb9dc31e97752c", "pic_id": "41c05373gy1hjx6cq8vqej20u00qwq6m", "photo_tag": 0, "type": "pic", "pic_status": 1}}, "is_paid": false, "mblog_vip_type": 0, "number_display_strategy": {"apply_scenario_flag": 3, "display_text_min_number": 1000000, "display_text": "100万+"}, "reposts_count": 0, "comments_count": 41, "attitudes_count": 197, "attitudes_status": 0, "isLongText": false, "mlevel": 0, "content_auth": 0, "is_show_bulletin": 2, "comment_manage_info": {"comment_permission_type": -1, "approval_comment_type": 0, "comment_sort_type": 0}, "share_repost_type": 0, "topic_struct": [{"title": "", "topic_url": "sinaweibo://searchall?containerid=231522&amp;q=%23%E5%88%98%E8%AF%97%E8%AF%97%E4%B8%80%E5%BF%B5%E5%85%B3%E5%B1%B1%23&amp;extparam=%23%E5%88%98%E8%AF%97%E8%AF%97%E4%B8%80%E5%BF%B5%E5%85%B3%E5%B1%B1%23", "topic_title": "刘诗诗一念关山", "actionlog": {"act_type": 1, "act_code": 300, "oid": "1022:231522d6d28ffabc100fb305785cfac101fef6", "uuid": 4767199259787354, "cardid": "", "lcardid": "", "uicode": "", "luicode": "", "fid": "1076031103123315_-_WEIBO_SECOND_PROFILE_WEIBO", "lfid": "", "ext": "mid:4968786448876113|rid:4_0_50_164789167795791383_0_0_0|short_url:|long_url:|comment_id:|miduid:1103123315|rootmid:4968786448876113|rootuid:1103123315|authorid:|uuid:4767199259787354|is_ad_weibo:0"}}], "mblogtype": 0, "showFeedRepost": false, "showFeedComment": false, "pictureViewerSign": false, "showPictureViewer": false, "rcList": [], "text": "九月已说过一念关山首播为网播。&lt;br /&gt;下周一起，蜀大侠×一念关山主题火锅店拉开宣传序幕。[小炭火][小炭火][小炭火]&lt;a href=\"//s.weibo.com/weibo?q=%23%E5%88%98%E8%AF%97%E8%AF%97%E4%B8%80%E5%BF%B5%E5%85%B3%E5%B1%B1%23\" target=\"_blank\"&gt;#刘诗诗一念关山#&lt;/a&gt; ​​​", "region_name": "发布于 广东", "customIcons": []}