{"visible": {"type": 0, "list_id": 0}, "created_at": "Fri Aug 23 13:19:50 +0800 2019", "id": 4408440531051056, "idstr": "4408440531051056", "mid": "4408440531051056", "mblogid": "I3xzL4pqw", "user": {"id": 1006657733, "idstr": "1006657733", "pc_new": 7, "screen_name": "广州天河木木", "profile_image_url": "https://tva4.sinaimg.cn/crop.0.1.640.640.50/3c0060c5jw8epkux26bryj20hs0hu76n.jpg?KID=imgbed,tva&Expires=1703002840&ssig=6d7my46tco", "profile_url": "/u/1006657733", "verified": false, "verified_type": 220, "domain": "", "weihao": "579100448", "avatar_large": "https://tva4.sinaimg.cn/crop.0.1.640.640.180/3c0060c5jw8epkux26bryj20hs0hu76n.jpg?KID=imgbed,tva&Expires=1703002840&ssig=370axTCHv2", "avatar_hd": "https://tva4.sinaimg.cn/crop.0.1.640.640.1024/3c0060c5jw8epkux26bryj20hs0hu76n.jpg?KID=imgbed,tva&Expires=1703002840&ssig=hrBcNzPGyi", "follow_me": false, "following": false, "mbrank": 7, "mbtype": 12, "v_plus": 0, "planet_video": false, "icon_list": [{"type": "vip", "data": {"mbrank": 7, "mbtype": 12, "svip": 0, "vvip": 0}}]}, "can_edit": false, "text_raw": "嘉兴，一座秀美的江南小镇。  ​​​", "textLength": 46, "annotations": [{"place": {"poiid": "B2094757D06FAAF54392", "title": "月河历史街区", "type": "checkin"}, "client_mblogid": "iPhone-3E3EF9AC-1616-45DE-A2C2-5BAE2263786A"}, {"mapi_request": true}], "source": "iPhone 7", "favorited": false, "rid": "15_0_50_163055323837014989_0_0_0", "pic_ids": ["3c0060c5ly1g69jhqcztzj21400u0q8x", "3c0060c5ly1g69jhpnvlfj21400u0n4j", "3c0060c5ly1g69jhr7wqgj20u014047f", "3c0060c5ly1g69jhs1njcj21400u0n7e", "3c0060c5ly1g69jhsx02oj20u014013m", "3c0060c5ly1g69jhtq7lfj21400u0dpr"], "geo": {"type": "Point", "coordinates": [30.770863, 120.750183]}, "pic_num": 6, "pic_infos": {"3c0060c5ly1g69jhqcztzj21400u0q8x": {"thumbnail": {"url": "https://wx3.sinaimg.cn/wap180/3c0060c5ly1g69jhqcztzj21400u0q8x.jpg", "width": 180, "height": 134, "cut_type": 1, "type": ""}, "bmiddle": {"url": "https://wx3.sinaimg.cn/wap360/3c0060c5ly1g69jhqcztzj21400u0q8x.jpg", "width": 360, "height": 269, "cut_type": 1, "type": ""}, "large": {"url": "https://wx3.sinaimg.cn/orj960/3c0060c5ly1g69jhqcztzj21400u0q8x.jpg", "width": 1280, "height": 960, "cut_type": 1, "type": ""}, "original": {"url": "https://wx3.sinaimg.cn/orj1080/3c0060c5ly1g69jhqcztzj21400u0q8x.jpg", "width": 1440, "height": 1080, "cut_type": 1, "type": ""}, "largest": {"url": "https://wx3.sinaimg.cn/large/3c0060c5ly1g69jhqcztzj21400u0q8x.jpg", "width": 1440, "height": 1080, "cut_type": 1, "type": ""}, "mw2000": {"url": "https://wx3.sinaimg.cn/mw2000/3c0060c5ly1g69jhqcztzj21400u0q8x.jpg", "width": 1440, "height": 1080, "cut_type": 1, "type": ""}, "object_id": "1042018:26c4d80bb68d1385bf87bb9836afafbb", "pic_id": "3c0060c5ly1g69jhqcztzj21400u0q8x", "photo_tag": 0, "type": "pic", "pic_status": 0}, "3c0060c5ly1g69jhpnvlfj21400u0n4j": {"thumbnail": {"url": "https://wx2.sinaimg.cn/wap180/3c0060c5ly1g69jhpnvlfj21400u0n4j.jpg", "width": 180, "height": 134, "cut_type": 1, "type": ""}, "bmiddle": {"url": "https://wx2.sinaimg.cn/wap360/3c0060c5ly1g69jhpnvlfj21400u0n4j.jpg", "width": 360, "height": 269, "cut_type": 1, "type": ""}, "large": {"url": "https://wx2.sinaimg.cn/orj960/3c0060c5ly1g69jhpnvlfj21400u0n4j.jpg", "width": 1280, "height": 960, "cut_type": 1, "type": ""}, "original": {"url": "https://wx2.sinaimg.cn/orj1080/3c0060c5ly1g69jhpnvlfj21400u0n4j.jpg", "width": 1440, "height": 1080, "cut_type": 1, "type": ""}, "largest": {"url": "https://wx2.sinaimg.cn/large/3c0060c5ly1g69jhpnvlfj21400u0n4j.jpg", "width": 1440, "height": 1080, "cut_type": 1, "type": ""}, "mw2000": {"url": "https://wx2.sinaimg.cn/mw2000/3c0060c5ly1g69jhpnvlfj21400u0n4j.jpg", "width": 1440, "height": 1080, "cut_type": 1, "type": ""}, "object_id": "1042018:3934a3ac7f5899dfbf66d1edfdc8cd8b", "pic_id": "3c0060c5ly1g69jhpnvlfj21400u0n4j", "photo_tag": 0, "type": "pic", "pic_status": 0}, "3c0060c5ly1g69jhr7wqgj20u014047f": {"thumbnail": {"url": "https://wx1.sinaimg.cn/wap180/3c0060c5ly1g69jhr7wqgj20u014047f.jpg", "width": 135, "height": 180, "cut_type": 1, "type": ""}, "bmiddle": {"url": "https://wx1.sinaimg.cn/wap360/3c0060c5ly1g69jhr7wqgj20u014047f.jpg", "width": 270, "height": 360, "cut_type": 1, "type": ""}, "large": {"url": "https://wx1.sinaimg.cn/orj960/3c0060c5ly1g69jhr7wqgj20u014047f.jpg", "width": 960, "height": 1280, "cut_type": 1, "type": ""}, "original": {"url": "https://wx1.sinaimg.cn/orj1080/3c0060c5ly1g69jhr7wqgj20u014047f.jpg", "width": 1080, "height": 1440, "cut_type": 1, "type": ""}, "largest": {"url": "https://wx1.sinaimg.cn/large/3c0060c5ly1g69jhr7wqgj20u014047f.jpg", "width": 1080, "height": 1440, "cut_type": 1, "type": ""}, "mw2000": {"url": "https://wx1.sinaimg.cn/mw2000/3c0060c5ly1g69jhr7wqgj20u014047f.jpg", "width": 1080, "height": 1440, "cut_type": 1, "type": ""}, "object_id": "1042018:0f5739bd949ac1580eabc2c44df55fce", "pic_id": "3c0060c5ly1g69jhr7wqgj20u014047f", "photo_tag": 0, "type": "pic", "pic_status": 0}, "3c0060c5ly1g69jhs1njcj21400u0n7e": {"thumbnail": {"url": "https://wx2.sinaimg.cn/wap180/3c0060c5ly1g69jhs1njcj21400u0n7e.jpg", "width": 180, "height": 134, "cut_type": 1, "type": ""}, "bmiddle": {"url": "https://wx2.sinaimg.cn/wap360/3c0060c5ly1g69jhs1njcj21400u0n7e.jpg", "width": 360, "height": 269, "cut_type": 1, "type": ""}, "large": {"url": "https://wx2.sinaimg.cn/orj960/3c0060c5ly1g69jhs1njcj21400u0n7e.jpg", "width": 1280, "height": 960, "cut_type": 1, "type": ""}, "original": {"url": "https://wx2.sinaimg.cn/orj1080/3c0060c5ly1g69jhs1njcj21400u0n7e.jpg", "width": 1440, "height": 1080, "cut_type": 1, "type": ""}, "largest": {"url": "https://wx2.sinaimg.cn/large/3c0060c5ly1g69jhs1njcj21400u0n7e.jpg", "width": 1440, "height": 1080, "cut_type": 1, "type": ""}, "mw2000": {"url": "https://wx2.sinaimg.cn/mw2000/3c0060c5ly1g69jhs1njcj21400u0n7e.jpg", "width": 1440, "height": 1080, "cut_type": 1, "type": ""}, "object_id": "1042018:038fafdbc396b1c92c9a3db4b86dd9cd", "pic_id": "3c0060c5ly1g69jhs1njcj21400u0n7e", "photo_tag": 0, "type": "pic", "pic_status": 0}, "3c0060c5ly1g69jhsx02oj20u014013m": {"thumbnail": {"url": "https://wx1.sinaimg.cn/wap180/3c0060c5ly1g69jhsx02oj20u014013m.jpg", "width": 135, "height": 180, "cut_type": 1, "type": ""}, "bmiddle": {"url": "https://wx1.sinaimg.cn/wap360/3c0060c5ly1g69jhsx02oj20u014013m.jpg", "width": 270, "height": 360, "cut_type": 1, "type": ""}, "large": {"url": "https://wx1.sinaimg.cn/orj960/3c0060c5ly1g69jhsx02oj20u014013m.jpg", "width": 960, "height": 1280, "cut_type": 1, "type": ""}, "original": {"url": "https://wx1.sinaimg.cn/orj1080/3c0060c5ly1g69jhsx02oj20u014013m.jpg", "width": 1080, "height": 1440, "cut_type": 1, "type": ""}, "largest": {"url": "https://wx1.sinaimg.cn/large/3c0060c5ly1g69jhsx02oj20u014013m.jpg", "width": 1080, "height": 1440, "cut_type": 1, "type": ""}, "mw2000": {"url": "https://wx1.sinaimg.cn/mw2000/3c0060c5ly1g69jhsx02oj20u014013m.jpg", "width": 1080, "height": 1440, "cut_type": 1, "type": ""}, "object_id": "1042018:fdcbfef94ffdc1d03711af2f774fdaf0", "pic_id": "3c0060c5ly1g69jhsx02oj20u014013m", "photo_tag": 0, "type": "pic", "pic_status": 0}, "3c0060c5ly1g69jhtq7lfj21400u0dpr": {"thumbnail": {"url": "https://wx3.sinaimg.cn/wap180/3c0060c5ly1g69jhtq7lfj21400u0dpr.jpg", "width": 180, "height": 134, "cut_type": 1, "type": ""}, "bmiddle": {"url": "https://wx3.sinaimg.cn/wap360/3c0060c5ly1g69jhtq7lfj21400u0dpr.jpg", "width": 360, "height": 269, "cut_type": 1, "type": ""}, "large": {"url": "https://wx3.sinaimg.cn/orj960/3c0060c5ly1g69jhtq7lfj21400u0dpr.jpg", "width": 1280, "height": 960, "cut_type": 1, "type": ""}, "original": {"url": "https://wx3.sinaimg.cn/orj1080/3c0060c5ly1g69jhtq7lfj21400u0dpr.jpg", "width": 1440, "height": 1080, "cut_type": 1, "type": ""}, "largest": {"url": "https://wx3.sinaimg.cn/large/3c0060c5ly1g69jhtq7lfj21400u0dpr.jpg", "width": 1440, "height": 1080, "cut_type": 1, "type": ""}, "mw2000": {"url": "https://wx3.sinaimg.cn/mw2000/3c0060c5ly1g69jhtq7lfj21400u0dpr.jpg", "width": 1440, "height": 1080, "cut_type": 1, "type": ""}, "object_id": "1042018:8def7861cb0b5f08501a0140bce47ca6", "pic_id": "3c0060c5ly1g69jhtq7lfj21400u0dpr", "photo_tag": 0, "type": "pic", "pic_status": 0}}, "is_paid": false, "mblog_vip_type": 0, "number_display_strategy": {"apply_scenario_flag": 3, "display_text_min_number": 1000000, "display_text": "100万+"}, "reposts_count": 0, "comments_count": 0, "attitudes_count": 2, "attitudes_status": 0, "isLongText": false, "mlevel": 0, "content_auth": 0, "is_show_bulletin": 2, "comment_manage_info": {"comment_permission_type": -1, "approval_comment_type": 0, "comment_sort_type": 0}, "share_repost_type": 0, "tag_struct": [{"tag_name": "月河历史街区", "tag_scheme": "sinaweibo://pageinfo?containerid=10080875cf4cf841cb969adeabbb5bbea4b2c8_-_lbs&lcardid=frompoi&extparam=frompoi", "url_type_pic": "https://h5.sinaimg.cn/upload/100/972/2022/06/13/timeline_location.png", "oid": "1022:100101B2094757D06FAAF54392", "otype": "place", "tag_type": 1, "tag_hidden": 2, "ori_url": "http://t.cn/z8AKCra", "actionlog": {"act_code": 2413, "oid": "1022:100101B2094757D06FAAF54392", "uicode": "", "luicode": "", "fid": "1076031006657733_-_WEIBO_SECOND_PROFILE_WEIBO", "ext": "orifid:"}, "desc": "江南水乡第11名", "is_checkin": 1}], "mblogtype": 0, "showFeedRepost": false, "showFeedComment": false, "pictureViewerSign": false, "showPictureViewer": false, "rcList": [], "text": "嘉兴，一座秀美的江南小镇。  ​​​", "customIcons": []}